MetaArray/__init__.py
MetaArray/plotting.py
metaarray-2.2.2.dist-info/METADATA
metaarray-2.2.2.dist-info/WHEEL
metaarray-2.2.2.dist-info/top_level.txt
metaarray-2.2.2.dist-info/RECORD
