Metadata-Version: 2.4
Name: MetaArray
Version: 2.2.2
Summary: N-dimensional array with metadata such as axis titles, units, and column names.
Home-page: https://github.com/outofculture/metaarray
Author: Luke Campagnola
Author-email: Luke Campagnola <luke.campagnola@gmail.com>
License: MIT
Project-URL: Homepage, https://github.com/outofculture/metaarray
Classifier: Development Status :: 5 - Production/Stable
Classifier: Environment :: Other Environment
Classifier: Intended Audience :: Science/Research
Classifier: License :: OSI Approved :: MIT License
Classifier: Operating System :: OS Independent
Classifier: Programming Language :: Python :: 3
Classifier: Programming Language :: Python
Classifier: Topic :: Scientific/Engineering
Classifier: Topic :: Software Development :: Libraries :: Python Modules
Requires-Python: >=3.7
Requires-Dist: numpy
Requires-Dist: h5df
Provides-Extra: plotting
Requires-Dist: pyqtgraph>=0.11.0; extra == "plotting"
Provides-Extra: dev
Requires-Dist: pytest>=7.0; extra == "dev"
Requires-Dist: pytest-qt>=4.0; extra == "dev"
Requires-Dist: black; extra == "dev"
Dynamic: author
Dynamic: home-page
Dynamic: requires-python
